tests/__init__.py
tests/conftest.py
tests/responses/__init__.py
tests/responses/indices.py
tests/responses/scan.py
tests/test_kibana/__init__.py
tests/test_kibana/test_access_log.py
tests/test_kibana/test_elastic_log.py
tests/test_kibana/test_request_log.py
tests/test_metrics/__init__.py
tests/test_metrics/conftest.py
tests/test_metrics/test_base.py
tests/test_metrics/test_counters.py
tests/test_utils/__init__.py
tests/test_utils/conftest.py
tests/test_utils/test_helpers.py
tests/test_utils/test_kibana.py
vuakhter/__init__.py
vuakhter/analyzer.py
vuakhter/base/__init__.py
vuakhter/base/access_log.py
vuakhter/base/base_log.py
vuakhter/base/requests_log.py
vuakhter/kibana/__init__.py
vuakhter/kibana/access_log.py
vuakhter/kibana/elastic_log.py
vuakhter/kibana/requests_log.py
vuakhter/metrics/__init__.py
vuakhter/metrics/base.py
vuakhter/metrics/counters.py
vuakhter/utils/__init__.py
vuakhter/utils/constants.py
vuakhter/utils/helpers.py
vuakhter/utils/kibana.py
vuakhter/utils/types.py
vuakhter-0.0.5.dist-info/METADATA
vuakhter-0.0.5.dist-info/WHEEL
vuakhter-0.0.5.dist-info/entry_points.txt
vuakhter-0.0.5.dist-info/top_level.txt
vuakhter-0.0.5.dist-info/RECORD
