Metadata-Version: 2.1
Name: vuakhter
Version: 0.0.5
Summary: Package to count usage statistics from ELK logs.
Home-page: UNKNOWN
Author: BestDoctor
Author-email: s.butkin@bestdoctor.ru
License: MIT
Keywords: kibana statistics
Platform: UNKNOWN
Classifier: Environment :: Console
Classifier: Operating System :: OS Independent
Classifier: Topic :: Software Development :: Libraries :: Python Modules
Classifier: Topic :: Software Development :: Quality Assurance
Classifier: Programming Language :: Python
Classifier: Programming Language :: Python :: 3.7
Classifier: Programming Language :: Python :: 3.8
Requires-Dist: setuptools
Requires-Dist: elasticsearch (<8.0.0,>=7.0.0)
Requires-Dist: elasticsearch-dsl (<8.0.0,>=7.0.0)
